bfscale/__init__.py
bfscale-2.0.0.dist-info/LICENSE
bfscale-2.0.0.dist-info/METADATA
bfscale-2.0.0.dist-info/WHEEL
bfscale-2.0.0.dist-info/top_level.txt
bfscale-2.0.0.dist-info/RECORD
