Metadata-Version: 2.1
Name: bfscale
Version: 2.0.0
Summary: Best fit image scaling
Author-email: GroveDG <grovedgdev@gmail.com>
Project-URL: Homepage, https://github.com/GroveDG/bfscale
Project-URL: Bug Tracker, https://github.com/GroveDG/bfscale/issues
Classifier: Programming Language :: Python :: 3
Classifier: License :: OSI Approved :: MIT License
Classifier: Operating System :: OS Independent
Requires-Python: >=3.5
License-File: LICENSE
Requires-Dist: numpy >=1.13
Provides-Extra: dev
Requires-Dist: imageio ; extra == 'dev'
